odoo/addons/l10n_br_nfse_barueri/README.rst
odoo/addons/l10n_br_nfse_barueri/__init__.py
odoo/addons/l10n_br_nfse_barueri/__manifest__.py
odoo/addons/l10n_br_nfse_barueri/constants/barueri.py
odoo/addons/l10n_br_nfse_barueri/i18n/l10n_br_nfse_barueri.pot
odoo/addons/l10n_br_nfse_barueri/i18n/pt_BR.po
odoo/addons/l10n_br_nfse_barueri/models/__init__.py
odoo/addons/l10n_br_nfse_barueri/models/document.py
odoo/addons/l10n_br_nfse_barueri/models/res_company.py
odoo/addons/l10n_br_nfse_barueri/readme/CONFIGURE.rst
odoo/addons/l10n_br_nfse_barueri/readme/CONTRIBUTORS.rst
odoo/addons/l10n_br_nfse_barueri/readme/DESCRIPTION.rst
odoo/addons/l10n_br_nfse_barueri/readme/INSTALL.rst
odoo/addons/l10n_br_nfse_barueri/readme/ROADMAP.rst
odoo/addons/l10n_br_nfse_barueri/readme/USAGE.rst
odoo/addons/l10n_br_nfse_barueri/static/description/icon.png
odoo/addons/l10n_br_nfse_barueri/static/description/index.html
odoo/addons/l10n_br_nfse_barueri/tests/__init__.py
odoo/addons/l10n_br_nfse_barueri/tests/test_fiscal_document_nfse_barueri.py
odoo/addons/l10n_br_nfse_barueri/tests/nfse/nfse.xml
odoo14_addon_l10n_br_nfse_barueri-14.0.1.2.0.dist-info/METADATA
odoo14_addon_l10n_br_nfse_barueri-14.0.1.2.0.dist-info/WHEEL
odoo14_addon_l10n_br_nfse_barueri-14.0.1.2.0.dist-info/top_level.txt
odoo14_addon_l10n_br_nfse_barueri-14.0.1.2.0.dist-info/RECORD
